<annotation>
	<folder>RC</folder>
	<filename>Img0389.jpg</filename>
	<path>C:\Users\USER\Desktop\RC\Img0389.jpg</path>
	<source>
		<database>Unknown</database>
	</source>
	<size>
		<width>450</width>
		<height>600</height>
		<depth>3</depth>
	</size>
	<segmented>0</segmented>
	<object>
		<name>RC</name>
		<pose>Unspecified</pose>
		<truncated>0</truncated>
		<difficult>0</difficult>
		<bndbox>
			<xmin>52</xmin>
			<ymin>231</ymin>
			<xmax>237</xmax>
			<ymax>426</ymax>
		</bndbox>
	</object>
</annotation>
